{
    "0": {
        "ID": "3866",
        "Inscrito": "04141071102",
        "Nome": "GABRIEL FARIA CARMO OLIVEIRA",
        "E-mail": "gabriel.faria@estudante.ifgoiano.edu.br"
    },
    "1": {
        "ID": "3867",
        "Inscrito": "08246029193",
        "Nome": "BLENDA GABRIELLY SOUZA MORAIS",
        "E-mail": "blenda.gabrielly@estudante.ifgoiano.edu.br"
    },
    "2": {
        "ID": "3871",
        "Inscrito": "06024729111",
        "Nome": "MATEUS BARROS MAC\\XC3\\XAADO",
        "E-mail": "mateus.barros@estudante.ifgoiano.edu.br"
    },
    "3": {
        "ID": "3900",
        "Inscrito": "06867453104",
        "Nome": "MATEUS BRUNOZI SILVA",
        "E-mail": "mateus.brunozi@estudante.ifgoiano.edu.br"
    },
    "4": {
        "ID": "4084",
        "Inscrito": "08544789145",
        "Nome": "GUSTAVO ROCHA MOREIRA",
        "E-mail": "gustavo.rocha@estudante.ifgoiano.edu.br"
    },
    "5": {
        "ID": "4200",
        "Inscrito": "70630317160",
        "Nome": "ALLANA GON\u00c7ALVES OLIVEIRA",
        "E-mail": "allana.oliveira@estudante.ifgoiano.edu.br"
    },
    "6": {
        "ID": "4201",
        "Inscrito": "71560031190",
        "Nome": "ISABELLA MAC\\XC3\\XAADO IN\\XC3\\XA1CIO LEITE",
        "E-mail": "isabella.macedo@estudante.ifgoiano.edu.br"
    },
    "7": {
        "ID": "4210",
        "Inscrito": "71060209152",
        "Nome": "RENAN RYUSUKE MIURA TOMIOKA",
        "E-mail": "renan.ryusuke@estudante.ifgoiano.edu.br"
    },
    "8": {
        "ID": "4288",
        "Inscrito": "70364485124",
        "Nome": "IAN CANDIDO MOREIRA SILVA",
        "E-mail": "ian.candido@estudante.ifgoiano.edu.br"
    },
    "9": {
        "ID": "4301",
        "Inscrito": "04090406145",
        "Nome": "PEDRO COSTA FREITAS",
        "E-mail": "pedro.freitas@estudante.ifgoiano.edu.br"
    },
    "10": {
        "ID": "4721",
        "Inscrito": "02898094102",
        "Nome": "GUILHERME CARVALHO FRANCO",
        "E-mail": "guilherme.carvalho@estudante.ifgoiano.edu.br"
    },
    "11": {
        "ID": "4722",
        "Inscrito": "06356396105",
        "Nome": "PEDRO RAPHAEL IN\\XC3\\XA1CIO GOMES",
        "E-mail": "pedro.gomes@estudante.ifgoiano.edu.br"
    },
    "12": {
        "ID": "4740",
        "Inscrito": "71155374100",
        "Nome": "WHENDERSON V\u00cdTOR ALVES ROQUE",
        "E-mail": "whenderson.roque@estudante.ifgoiano.edu.br"
    },
    "13": {
        "ID": "4770",
        "Inscrito": "05122212198",
        "Nome": "MICKAEL VICTOR GONCALVES DA COSTA",
        "E-mail": "mickaelcosta005@gmail.com"
    },
    "14": {
        "ID": "4889",
        "Inscrito": "04184292194",
        "Nome": "ANNA BEATRIZ CARLOS DE OLIVEIRA",
        "E-mail": "anna.carlos@estudante.ifgoiano.edu.br"
    },
    "15": {
        "ID": "6323",
        "Inscrito": "07252191141",
        "Nome": "KARLLA MOREIRA DE OLIVEIRA",
        "E-mail": "karllamoreira911@gmail.com"
    }
}